mosayc/__init__.py
mosayc/cli.py
mosayc/mosayc.py
mosayc/parameters.py
mosayc-0.1.0.dist-info/METADATA
mosayc-0.1.0.dist-info/WHEEL
mosayc-0.1.0.dist-info/entry_points.txt
mosayc-0.1.0.dist-info/licenses/AUTHORS.md
mosayc-0.1.0.dist-info/RECORD
