Metadata-Version: 2.4
Name: mosayc
Version: 0.1.0
Summary: Mosayc turns a main picture into a mosaic of smaller pictures.
Project-URL: Repository, https://github.com/balouf/mosayc
Project-URL: Documentation, https://balouf.github.io/mosayc
Author-email: Fabien Mathieu <fabien.mathieu@normalesup.org>
Maintainer-email: Fabien Mathieu <fabien.mathieu@normalesup.org>
License-Expression: MIT
License-File: AUTHORS.md
Requires-Python: >=3.10
Requires-Dist: click>=8.1.8
Requires-Dist: numpy>=2.2.6
Requires-Dist: pillow>=11.2.1
Requires-Dist: pydantic>=2.11.7
Requires-Dist: pyyaml>=6.0.2
Requires-Dist: tqdm>=4.67.1
